web/__init__.py
web/__main__.py
web/dt.py
web/framework/__init__.py
web/framework/letsencrypt.py
web/framework/newmath.py
web/framework/passphrases.json
web/framework/passphrases.py
web/framework/static/measure.png
web/framework/static/solarized-site.css
web/framework/static/solarized.css
web/framework/static/sw.min.js
web/framework/static/ubuntu-mono-powerline.woff2
web/framework/static/vosk-recognizer-processor.js
web/framework/static/web.css
web/framework/static/web.js
web/framework/templates/__init__.py
web/framework/templates/nginx.conf
web/framework/templates/nginx_host.conf
web/framework/templates/nginx_host_body.conf
web/framework/templates/nginx_tor_host.conf
web/framework/templates/redis.conf
web/framework/templates/render_breadcrumbs.html
web/framework/templates/supervisor.conf
web/framework/templates/traceback.html
web/framework/util.py
web/headers/__init__.py
web/headers/entity.py
web/headers/general.py
web/headers/request.py
web/headers/response.py
web/headers/util.py
web/host/__init__.py
web/host/admin/__init__.py
web/host/admin/templates/__init__.py
web/host/admin/templates/application.html
web/host/admin/templates/choose_domain.html
web/host/admin/templates/domains.html
web/host/admin/templates/index.html
web/host/admin/templates/template.html
web/host/providers.py
web/host/templates/__init__.py
web/host/templates/etherpad.json
web/host/templates/mediasoup.js
web/host/templates/nginx.conf
web/host/templates/nginx_acme_challenge.conf
web/host/templates/nginx_application.conf
web/host/templates/nginx_index.html
web/host/templates/nginx_site.conf
web/host/templates/nginx_ssl_params.conf
web/host/test_host.py
web/markdown/__init__.py
web/markdown/hyph_en_US.dic
web/markdown/hyphenator.py
web/markdown/titlecase.py
web/response/__init__.py
web/response/clienterror.py
web/response/informational.py
web/response/redirection.py
web/response/servererror.py
web/response/success.py
web/response/util.py
web/slrzd.py
web/templating/__init__.py
webint-0.1.96.dist-info/METADATA
webint-0.1.96.dist-info/entry_points.txt
webint-0.1.96.dist-info/WHEEL
webint-0.1.96.dist-info/RECORD
